pyobs/__init__.py
pyobs/core.py
sais_pyobs-0.1.6.dist-info/METADATA
sais_pyobs-0.1.6.dist-info/WHEEL
sais_pyobs-0.1.6.dist-info/top_level.txt
sais_pyobs-0.1.6.dist-info/RECORD
