Metadata-Version: 2.4
Name: sais-pyobs
Version: 0.1.6
Summary: A high-performance OBS transfer tool for AI datasets.
Author-email: huangjiajia <your.email@example.com>
License: MIT
Project-URL: Homepage, https://github.com/huangpd/pyobs
Project-URL: Source, https://github.com/huangpd/pyobs
Project-URL: Issues, https://github.com/huangpd/pyobs/issues
Requires-Python: >=3.10
Requires-Dist: requests>=2.25.0
Requires-Dist: huaweicloud-sdk-python-obs>=3.21.8
Requires-Dist: tqdm
